form_designer/__init__.py
form_designer/admin.py
form_designer/apps.py
form_designer/contents.py
form_designer/default_field_types.py
form_designer/models.py
form_designer/locale/cs/LC_MESSAGES/django.mo
form_designer/locale/cs/LC_MESSAGES/django.po
form_designer/locale/de/LC_MESSAGES/django.mo
form_designer/locale/de/LC_MESSAGES/django.po
form_designer/migrations/0001_initial.py
form_designer/migrations/0002_rename_name_formfield__old_name_and_more.py
form_designer/migrations/0003_formfield_name_alter_formfield__old_name_and_more.py
form_designer/migrations/0004_alter_formsubmission_options_and_more.py
form_designer/migrations/0005_remove_form_config_json_form_config_and_more.py
form_designer/migrations/__init__.py
form_designer/static/form_designer/admin.css
form_designer/templates/admin/form_designer/form/change_form.html
form_designer/templates/admin/form_designer/formsubmission/change_form.html
form_designer/templates/content/form/form.html
form_designer-0.27.2.dist-info/METADATA
form_designer-0.27.2.dist-info/WHEEL
form_designer-0.27.2.dist-info/licenses/LICENSE
form_designer-0.27.2.dist-info/RECORD
