Metadata-Version: 2.4
Name: form-designer
Version: 0.27.2
Summary: Form Designer
Project-URL: Homepage, https://github.com/feincms/form-designer/
Author-email: Matthias Kestenholz <mk@feinheit.ch>
License: BSD-3-Clause
License-File: LICENSE
Classifier: Development Status :: 5 - Production/Stable
Classifier: Environment :: Web Environment
Classifier: Framework :: Django
Classifier: Intended Audience :: Developers
Classifier: License :: OSI Approved :: BSD License
Classifier: Operating System :: OS Independent
Classifier: Programming Language :: Python
Classifier: Programming Language :: Python :: 3 :: Only
Classifier: Programming Language :: Python :: 3.9
Classifier: Programming Language :: Python :: 3.10
Classifier: Programming Language :: Python :: 3.11
Classifier: Programming Language :: Python :: 3.12
Classifier: Programming Language :: Python :: 3.13
Classifier: Programming Language :: Python :: 3.14
Classifier: Topic :: Internet :: WWW/HTTP :: Dynamic Content
Classifier: Topic :: Software Development
Requires-Python: >=3.9
Requires-Dist: django-admin-ordering
Requires-Dist: xlsxdocument
Provides-Extra: tests
Requires-Dist: coverage; extra == 'tests'
Requires-Dist: django-mptt; extra == 'tests'
Requires-Dist: django-recaptcha>=4; extra == 'tests'
Requires-Dist: feincms; extra == 'tests'
